{
  "generated_at": "2026-03-24T14:20:46.057Z",
  "currentlyReading": [
    {
      "title": "The Brothers Karamazov",
      "author": "Fyodor Dostoevsky",
      "rating": 0,
      "avgRating": 4.37,
      "dateAdded": "Mon, 16 Mar 2026 20:49:45 -0700",
      "published": "1880",
      "numPages": 796,
      "imageUrl": "https://i.gr-assets.com/images/S/compressed.photo.goodreads.com/books/1427728126l/4934._SX98_.jpg",
      "bookId": "4934",
      "link": "https://www.goodreads.com/review/show/8430600555?utm_medium=api&utm_source=rss"
    }
  ],
  "recentlyRead": [
    {
      "title": "Wuthering Heights",
      "author": "Emily Brontë",
      "rating": 3,
      "avgRating": 3.91,
      "dateAdded": "Mon, 23 Mar 2026 08:50:35 -0700",
      "published": "1847",
      "numPages": 359,
      "imageUrl": "https://i.gr-assets.com/images/S/compressed.photo.goodreads.com/books/1478641029l/32929156._SX98_.jpg",
      "bookId": "32929156",
      "link": "https://www.goodreads.com/review/show/8418039770?utm_medium=api&utm_source=rss"
    },
    {
      "title": "Children of Dune (Dune #3)",
      "author": "Frank Herbert",
      "rating": 4,
      "avgRating": 3.96,
      "dateAdded": "Sat, 07 Mar 2026 10:54:12 -0800",
      "published": "1976",
      "numPages": 609,
      "imageUrl": "https://i.gr-assets.com/images/S/compressed.photo.goodreads.com/books/1564783201l/44492286._SY160_.jpg",
      "bookId": "44492286",
      "link": "https://www.goodreads.com/review/show/8418072991?utm_medium=api&utm_source=rss"
    },
    {
      "title": "Dune Messiah (Dune #2)",
      "author": "Frank Herbert",
      "rating": 4,
      "avgRating": 3.89,
      "dateAdded": "Sat, 07 Mar 2026 10:53:58 -0800",
      "published": "1969",
      "numPages": 336,
      "imageUrl": "https://i.gr-assets.com/images/S/compressed.photo.goodreads.com/books/1577043824l/44492285._SY160_.jpg",
      "bookId": "44492285",
      "link": "https://www.goodreads.com/review/show/8418072429?utm_medium=api&utm_source=rss"
    },
    {
      "title": "Dune (Dune, #1)",
      "author": "Frank Herbert",
      "rating": 5,
      "avgRating": 4.34,
      "dateAdded": "Sat, 07 Mar 2026 10:53:32 -0800",
      "published": "1965",
      "numPages": 658,
      "imageUrl": "https://i.gr-assets.com/images/S/compressed.photo.goodreads.com/books/1555447414l/44767458._SX98_.jpg",
      "bookId": "44767458",
      "link": "https://www.goodreads.com/review/show/8418071378?utm_medium=api&utm_source=rss"
    },
    {
      "title": "Atlas Shrugged",
      "author": "Ayn Rand",
      "rating": 5,
      "avgRating": 3.67,
      "dateAdded": "Sat, 07 Mar 2026 10:50:56 -0800",
      "published": "1957",
      "numPages": 1168,
      "imageUrl": "https://i.gr-assets.com/images/S/compressed.photo.goodreads.com/books/1405868167l/662._SX98_.jpg",
      "bookId": "662",
      "link": "https://www.goodreads.com/review/show/8418065357?utm_medium=api&utm_source=rss"
    }
  ],
  "totalPages": 3325,
  "profileUrl": "https://www.goodreads.com/user/show/199381877"
}